Encryptor/__init__.py
Encryptor/enc.py
Py_Encryptor-2.3.dist-info/LICENSE
Py_Encryptor-2.3.dist-info/METADATA
Py_Encryptor-2.3.dist-info/WHEEL
Py_Encryptor-2.3.dist-info/top_level.txt
Py_Encryptor-2.3.dist-info/RECORD
