Metadata-Version: 2.1
Name: Py-Encryptor
Version: 2.3
Summary: Encrypt Strings And Files With Bush Encryption (OR) AES Encryption (OR) Fernet Encryption
Home-page: https://github.com/pmk456/Encryptor
Author: Patan Musthakheem
Author-email: patanmusthakheem786@gmail.com
License: Apache 2.0
Project-URL: Documentation, https://github.com/pmk456/Encryptor/blob/main/README.md
Project-URL: Source, https://github.com/pmk456/Encryptor
Project-URL: Tracker, https://github.com/pmk456/Encryptor/issues
Keywords: encryption,encryptors,aes,bush
Platform: UNKNOWN
Classifier: License :: OSI Approved :: Apache Software License
Requires-Python: >=3.5
License-File: LICENSE
Requires-Dist: pycryptodome (>=3.9.6)
Requires-Dist: cryptography (>=3.4.7)
Requires-Dist: Bush-Encryption (>=0.3)
Requires-Dist: rsa (>=4.7.2)
